xarchgen/__init__.py
xarchgen/cli.py
xarchgen/database.py
xarchgen/utils.py
xarchgen/generators/__init__.py
xarchgen/generators/base.py
xarchgen/generators/dotnet.py
xarchgen/generators/fastapi.py
xarchgen/templates/dotnetapi/ai_assistants/claude.md.j2
xarchgen/templates/dotnetapi/ai_assistants/cursorrules.txt.j2
xarchgen/templates/dotnetapi/application/application_di_extensions.cs.j2
xarchgen/templates/dotnetapi/application/application_service.cs.j2
xarchgen/templates/dotnetapi/application/application_service_interface.cs.j2
xarchgen/templates/dotnetapi/application/controller.cs.j2
xarchgen/templates/dotnetapi/application/mapping_profile.cs.j2
xarchgen/templates/dotnetapi/application/program.cs.j2
xarchgen/templates/dotnetapi/configuration/appsettings.json.j2
xarchgen/templates/dotnetapi/configuration/sensitive_data_examples.cs.j2
xarchgen/templates/dotnetapi/configuration/serilog_configuration.cs.j2
xarchgen/templates/dotnetapi/core/entity.cs.j2
xarchgen/templates/dotnetapi/core/error.cs.j2
xarchgen/templates/dotnetapi/core/result.cs.j2
xarchgen/templates/dotnetapi/dtos/create_dto.cs.j2
xarchgen/templates/dotnetapi/dtos/dto_validator.cs.j2
xarchgen/templates/dotnetapi/dtos/pagination_request.cs.j2
xarchgen/templates/dotnetapi/dtos/update_dto.cs.j2
xarchgen/templates/dotnetapi/infrastructure/infrastructure_di_extensions.cs.j2
xarchgen/templates/dotnetapi/infrastructure/repository_dapper.cs.j2
xarchgen/templates/dotnetapi/infrastructure/repository_interface.cs.j2
xarchgen/templates/dotnetapi/infrastructure/sql_query_builder.cs.j2
xarchgen/templates/dotnetapi/middleware/correlation_middleware.cs.j2
xarchgen/templates/dotnetapi/middleware/request_logging_middleware.cs.j2
xarchgen/templates/dotnetapi/project/application.csproj.j2
xarchgen/templates/dotnetapi/project/core.csproj.j2
xarchgen/templates/dotnetapi/project/infrastructure.csproj.j2
xarchgen/templates/dotnetapi/project/solution.sln.j2
xarchgen/templates/dotnetapi/project/webapi.csproj.j2
xarchgen-0.1.1.dist-info/licenses/LICENSE
xarchgen-0.1.1.dist-info/METADATA
xarchgen-0.1.1.dist-info/WHEEL
xarchgen-0.1.1.dist-info/entry_points.txt
xarchgen-0.1.1.dist-info/top_level.txt
xarchgen-0.1.1.dist-info/RECORD
