Metadata-Version: 2.4
Name: xarchgen
Version: 0.1.1
Summary: Generate Clean Architecture backend applications (FastAPI/DotNet) from PostgreSQL schemas
Author-email: Xcdify <hd@xcdify.com>
License: MIT
Project-URL: Homepage, https://github.com/xcdify/xarchgen
Project-URL: Documentation, https://github.com/xcdify/xarchgen#readme
Project-URL: Repository, https://github.com/xcdify/xarchgen
Project-URL: Issues, https://github.com/xcdify/xarchgen/issues
Keywords: code-generator,fastapi,dotnet,clean-architecture,postgresql,backend
Classifier: Development Status :: 4 - Beta
Classifier: Intended Audience :: Developers
Classifier: License :: OSI Approved :: MIT License
Classifier: Programming Language :: Python :: 3
Classifier: Programming Language :: Python :: 3.11
Classifier: Programming Language :: Python :: 3.12
Classifier: Topic :: Software Development :: Code Generators
Classifier: Topic :: Software Development :: Libraries :: Python Modules
Requires-Python: >=3.11
License-File: LICENSE
Requires-Dist: psycopg2-binary>=2.9.9
Requires-Dist: jinja2>=3.1.3
Requires-Dist: pydantic>=2.6.0
Requires-Dist: python-dotenv>=1.0.0
Requires-Dist: click>=8.1.0
Requires-Dist: rich>=13.0.0
Requires-Dist: typing-extensions>=4.0.0
Provides-Extra: dev
Requires-Dist: pytest>=7.0.0; extra == "dev"
Requires-Dist: pytest-cov>=4.0.0; extra == "dev"
Requires-Dist: black>=23.0.0; extra == "dev"
Requires-Dist: ruff>=0.1.0; extra == "dev"
Requires-Dist: mypy>=1.0.0; extra == "dev"
Dynamic: license-file
